langextract_azureopenai/__init__.py
langextract_azureopenai/provider.py
langextract_azureopenai/schema.py
langextract_azureopenai_benjikcf-0.1.0.dist-info/licenses/LICENSE
langextract_azureopenai_benjikcf-0.1.0.dist-info/METADATA
langextract_azureopenai_benjikcf-0.1.0.dist-info/WHEEL
langextract_azureopenai_benjikcf-0.1.0.dist-info/entry_points.txt
langextract_azureopenai_benjikcf-0.1.0.dist-info/top_level.txt
langextract_azureopenai_benjikcf-0.1.0.dist-info/RECORD
