Metadata-Version: 2.4
Name: langextract-azureopenai-benjikcf
Version: 0.1.0
Summary: LangExtract provider plugin for AzureOpenAI
License: Apache-2.0
Requires-Python: >=3.10
License-File: LICENSE
Requires-Dist: langextract>=1.0.0
Dynamic: license-file
